opveclib/__init__.py
opveclib/dynamiclibop.cc
opveclib/dynamiclibop.h
opveclib/expression.py
opveclib/language.proto
opveclib/language_pb2.py
opveclib/local.py
opveclib/operator.py
opveclib/testcop.cc
opveclib/testcudaop.cc
opveclib/threadpool.h
opveclib/examples/__init__.py
opveclib/examples/conv1D.py
opveclib/examples/main_graph.py
opveclib/examples/test_accumulate.py
opveclib/examples/test_expm1.py
opveclib/examples/test_graph.py
opveclib/examples/test_log1p.py
opveclib/examples/test_perf_accumulate.py
opveclib/stdops/__init__.py
opveclib/stdops/math.py
opveclib/stdops/test_math.py
opveclib/test/__init__.py
opveclib/test/addcpu.cpp
opveclib/test/addgpu.cu
opveclib/test/test_arange.py
opveclib/test/test_binary_math.py
opveclib/test/test_clip.py
opveclib/test/test_dot_product.py
opveclib/test/test_dynamiclib_addgpu.py
opveclib/test/test_expressions.py
opveclib/test/test_gradients.py
opveclib/test/test_limits.py
opveclib/test/test_multiple_outputs.py
opveclib/test/test_operator.py
opveclib/test/test_operator_merge.py
opveclib/test/test_tensorflow_integration.py
opveclib/test/test_unary_math.py
opveclib-1.0.2.dist-info/DESCRIPTION.rst
opveclib-1.0.2.dist-info/METADATA
opveclib-1.0.2.dist-info/RECORD
opveclib-1.0.2.dist-info/WHEEL
opveclib-1.0.2.dist-info/metadata.json
opveclib-1.0.2.dist-info/top_level.txt
