Metadata-Version: 2.0
Name: opveclib
Version: 1.0.2
Summary: Operator Vectorization Library
Home-page: https://github.com/opveclib/opveclib/
Author: Hewlett Packard Labs
Author-email: UNKNOWN
License: Apache 2.0
Platform: UNKNOWN
Requires-Dist: numpy (>=1.11.0)
Requires-Dist: protobuf (>=3.0.0)
Requires-Dist: six (>=1.10.0)
Requires-Dist: tensorflow (>=0.11.0)
